bendev/__init__.py
bendev/device.py
bendev/exceptions.py
bendev/file_device.py
bendev-0.3.3.dist-info/LICENSE
bendev-0.3.3.dist-info/METADATA
bendev-0.3.3.dist-info/WHEEL
bendev-0.3.3.dist-info/top_level.txt
bendev-0.3.3.dist-info/RECORD
